[
    {
        "register_num": "185002001",
        "name": "AADHITHYA B KAILASH",
        "url": "https://www.linkedin.com/in/aadhithya-b-kailash-195b115b/"
    },
    {
        "register_num": "185002002",
        "name": "ABISHEK M",
        "url": "https://www.linkedin.com/in/abishek-m-5583491b9/"
    },
    {
        "register_num": "185002003",
        "name": "ADITHYA R",
        "url": "https://www.linkedin.com/in/adithya-r-7853671a7/"
    },
    {
        "register_num": "185002004",
        "name": "AISHWARYA VAIKUNDAM R",
        "url": "https://www.linkedin.com/in/aishwarya-vaikundam-r-a8716018a/"
    },
    {
        "register_num": "185002005",
        "name": "AJAY A ",
        "url": "https://www.linkedin.com/in/ajay-a-19315118a"
    },
    {
        "register_num": "185002006",
        "name": "AJAY R",
        "url": "https://www.linkedin.com/in/ajay-ramesh-31516718a/"
    },
    {
        "register_num": "185002007",
        "name": "AKARVIN RAJA PRAJAN S A J",
        "url": "https://www.linkedin.com/in/akarvin-raja-prajan-408209178/"
    },
    {
        "register_num": "185002008",
        "name": "AKSHAYA S",
        "url": "https://www.linkedin.com/in/akshaya-s-5a7a57213/"
    },
    {
        "register_num": "185002009",
        "name": "AKSHAYA V S",
        "url": "Not Found"
    },
    {
        "register_num": "185002010",
        "name": "ALFRIN A J",
        "url": "https://www.linkedin.com/in/alfrin-aj/"
    },
    {
        "register_num": "185002011",
        "name": "AMRITH M",
        "url": "https://www.linkedin.com/in/amrith-m-2a081a205/"
    },
    {
        "register_num": "185002012",
        "name": "AMRITHA S",
        "url": "Not Found"
    },
    {
        "register_num": "185002013",
        "name": "ANOOSH SOLAYAPPAN V",
        "url": "https://www.linkedin.com/in/anoosh-solayappan/"
    },
    {
        "register_num": "185002014",
        "name": "ARAVIND ANGAPPAN R",
        "url": "https://www.linkedin.com/in/aravind-angappan-631992219/"
    },
    {
        "register_num": "185002015",
        "name": "ARUN K S",
        "url": "https://www.linkedin.com/in/arun-ks-b107bb169/"
    },
    {
        "register_num": "185002016",
        "name": "ARUN KUMAR R",
        "url": "Not Found"
    },
    {
        "register_num": "185002017",
        "name": "ARUN LAXMAN A",
        "url": "https://www.linkedin.com/in/arun-laxman-a-01234/"
    },
    {
        "register_num": "185002018",
        "name": "BADRI NARAYANAN M",
        "url": "https://www.linkedin.com/in/mbadrinarayanan/"
    },
    {
        "register_num": "185002019",
        "name": "BADRINARAYANAN R",
        "url": "https://www.linkedin.com/in/badrinarayanan-r-234a38162/"
    },
    {
        "register_num": "185002020",
        "name": "BOYAPATI YAGNAVI CHOWDARI",
        "url": "https://www.linkedin.com/in/yagnavi/"
    },
    {
        "register_num": "185002021",
        "name": "BRINDHA K",
        "url": "https://www.linkedin.com/in/brindhak/"
    },
    {
        "register_num": "185002022",
        "name": "BRINDHA S",
        "url": "Not Found"
    },
    {
        "register_num": "185002023",
        "name": "BRYAN RONNIE J",
        "url": "https://www.linkedin.com/in/bryan-ronnie/"
    },
    {
        "register_num": "185002024",
        "name": "CHUNDURI HAINDHAVI",
        "url": "https://www.linkedin.com/in/haindhavi-chunduri-4a03a9190/"
    },
    {
        "register_num": "185002025",
        "name": "DINESH KUMAR E",
        "url": "Not Found"
    },
    {
        "register_num": "185002026",
        "name": "DIVYA R",
        "url": "Not Found"
    },
    {
        "register_num": "185002027",
        "name": "DIVYADHARSHINI R",
        "url": "https://www.linkedin.com/in/divyadharshini-r-25315b18a/"
    },
    {
        "register_num": "185002028",
        "name": "ELAKKIYA P",
        "url": "https://www.linkedin.com/in/elakkiya-pugazhendhi-a547a41b1/"
    },
    {
        "register_num": "185002029",
        "name": "GHANTA SANDHYA RANI",
        "url": "Not Found"
    },
    {
        "register_num": "185002030",
        "name": "HAMSINI R S",
        "url": "https://www.linkedin.com/in/r-s-hamsini-a1135818a/"
    },
    {
        "register_num": "185002031",
        "name": "HARISH SHARMA V",
        "url": "Not Found"
    },
    {
        "register_num": "185002032",
        "name": "HARRISON VIJAY J",
        "url": "https://www.linkedin.com/in/harrison-vijay/"
    },
    {
        "register_num": "185002033",
        "name": "HARSHAVARDHINI G",
        "url": "https://www.linkedin.com/in/harshavardhini-g-2000/"
    },
    {
        "register_num": "185002034",
        "name": "HARSHENE R",
        "url": "https://www.linkedin.com/in/harshene-ravindran/\\"
    },
    {
        "register_num": "185002035",
        "name": "HARSHINI B",
        "url": "Not Found"
    },
    {
        "register_num": "185002036",
        "name": "HARSHINI S",
        "url": "Not Found"
    },
    {
        "register_num": "185002037",
        "name": "INAMANAMELLURU K V LAKSHMI KALYANI",
        "url": "https://www.linkedin.com/in/lakshmi-kalyani-ikv-3204a2212/"
    },
    {
        "register_num": "185002038",
        "name": "INDIRAPRIYADARSHINI A",
        "url": "https://www.linkedin.com/in/indirapriyadarshini-a/"
    },
    {
        "register_num": "185002039",
        "name": "JAJULA ABHAYA CHETNA ",
        "url": "https://www.linkedin.com/in/abhaya-chetna/"
    },
    {
        "register_num": "185002040",
        "name": "JANICE MARIAN JOCKIM",
        "url": "https://www.linkedin.com/in/janice-jockim-1712d/"
    },
    {
        "register_num": "185002041",
        "name": "JAYESH L",
        "url": "https://www.linkedin.com/in/jayesh-laxman-1b147a193/"
    },
    {
        "register_num": "185002042",
        "name": "JEEVIKA B",
        "url": "https://www.linkedin.com/in/jeevika-b-26042000/"
    },
    {
        "register_num": "185002043",
        "name": "JIFRY ROSE R V",
        "url": "Not Found"
    },
    {
        "register_num": "185002044",
        "name": "JITHESH REDDY M",
        "url": "https://www.linkedin.com/in/jithesh-reddy-66a58a18a/"
    },
    {
        "register_num": "185002045",
        "name": "JOTHIKA R",
        "url": "https://www.linkedin.com/in/jothika-raja-54a28718a/"
    },
    {
        "register_num": "185002046",
        "name": "KAMPALLI KISHORE KUMAR",
        "url": "Not Found"
    },
    {
        "register_num": "185002047",
        "name": "KATEM BHAVANA",
        "url": "https://www.linkedin.com/in/katem-bhavana-22859217b/"
    },
    {
        "register_num": "185002048",
        "name": "KATTI SIDDHARTHA SANKAR",
        "url": "https://www.linkedin.com/in/siddhartha-sankar-katti-86a085203/"
    },
    {
        "register_num": "185002049",
        "name": "KEERTIVAAS S",
        "url": "https://www.linkedin.com/in/keertivaas-sankaranarayanan-a6517218a/"
    },
    {
        "register_num": "185002050",
        "name": "KOMMALAPATI VIKAS CHOWDARY",
        "url": "Not Found"
    },
    {
        "register_num": "185002051",
        "name": "KOUSHIKA PADMANABAN",
        "url": "https://www.linkedin.com/in/koushika-padmanaban-b706b718a/"
    },
    {
        "register_num": "185002052",
        "name": "KRITHIK SHARAN S A",
        "url": "Not Found"
    },
    {
        "register_num": "185002053",
        "name": "LAKSHANYA P",
        "url": "https://www.linkedin.com/in/lakshanya-p/"
    },
    {
        "register_num": "185002054",
        "name": "MADHAVAN V",
        "url": "https://www.linkedin.com/in/madhavan-v-a38656180/"
    },
    {
        "register_num": "185002055",
        "name": "MADHUMITA L",
        "url": "Not Found"
    },
    {
        "register_num": "185002056",
        "name": "MAHIMA",
        "url": "https://www.linkedin.com/in/mahimasundarp/"
    },
    {
        "register_num": "185002057",
        "name": "MANDADI VYSHNAVI",
        "url": "https://www.linkedin.com/in/vyshnavi-mandadi-67816118a/"
    },
    {
        "register_num": "185002058",
        "name": "MANIKANDAN S",
        "url": "https://www.linkedin.com/in/manikandan-s-435820218/"
    },
    {
        "register_num": "185002059",
        "name": "MANISHA G",
        "url": "Not Found"
    },
    {
        "register_num": "185002060",
        "name": "MEGHANA K",
        "url": "https://www.linkedin.com/in/meghanakrish/"
    },
    {
        "register_num": "185002061",
        "name": "METTUKURU AVINASH REDDY",
        "url": "https://www.linkedin.com/in/avinash-reddy-mettukuru-8340b91b7/"
    },
    {
        "register_num": "185002062",
        "name": "MICHAEL SUGUNA KUMAR V",
        "url": "Not Found"
    },
    {
        "register_num": "185002063",
        "name": "MOHAMED JAMEEL A H",
        "url": "https://www.linkedin.com/in/mohamed-jameel-a-h-91b9a3192/"
    },
    {
        "register_num": "185002301",
        "name": "JESONE C J SAM",
        "url": "https://www.linkedin.com/in/jesone-sam-24bb15210/"
    },
    {
        "register_num": "185002302",
        "name": "KISHAN RAJ R",
        "url": "Not Found"
    },
    {
        "register_num": "185002304",
        "name": "PRAVEEN KUMAR P",
        "url": "https://www.linkedin.com/in/praveen-kumar-p-150b4b210/"
    },
    {
        "register_num": "185002306",
        "name": "RAMAMOORTHY R",
        "url": "Not Found"
    }
]